deepagent_runner/__init__.py
deepagent_runner/agent.py
deepagent_runner/backend.py
deepagent_runner/cli.py
deepagent_runner/config.py
deepagent_runner/session.py
deepagent_runner/session_manager.py
deepagent_runner/shell_exec.py
deepagent_runner-0.1.2.dist-info/METADATA
deepagent_runner-0.1.2.dist-info/WHEEL
deepagent_runner-0.1.2.dist-info/entry_points.txt
deepagent_runner-0.1.2.dist-info/RECORD
