Metadata-Version: 2.4
Name: deepagent-runner
Version: 0.1.2
Summary: A terminal application for running DeepAgent in a workspace directory
Author: DeepAgent Runner Team
License: MIT
Requires-Python: >=3.11
Requires-Dist: deepagents>=0.1.0
Requires-Dist: langchain-openai>=0.2.0
Requires-Dist: langchain>=0.3.0
Requires-Dist: langgraph>=0.2.0
Requires-Dist: pydantic-settings>=2.0.0
Requires-Dist: pydantic>=2.0.0
Requires-Dist: python-dotenv>=1.0.0
Requires-Dist: questionary>=2.0.0
Requires-Dist: rich>=13.0.0
Requires-Dist: typer>=0.12.0
Provides-Extra: dev
Requires-Dist: black>=24.0.0; extra == 'dev'
Requires-Dist: mypy>=1.8.0; extra == 'dev'
Requires-Dist: pytest>=8.0.0; extra == 'dev'
Requires-Dist: ruff>=0.3.0; extra == 'dev'
Provides-Extra: tavily
Requires-Dist: tavily-python>=0.3.0; extra == 'tavily'
